dsnap/__init__.py
dsnap/__main__.py
dsnap/files/Vagrantfile
dsnap/main.py
dsnap/prompt.py
dsnap/snapshot.py
dsnap/utils.py
dsnap-1.0.1.dist-info/LICENSE
dsnap-1.0.1.dist-info/METADATA
dsnap-1.0.1.dist-info/WHEEL
dsnap-1.0.1.dist-info/entry_points.txt
dsnap-1.0.1.dist-info/RECORD
