Metadata-Version: 2.3
Name: dsnap
Version: 1.0.1
Summary: Utility for downloading EBS snapshots using the EBS Direct API's
Author: Ryan Gerstenkorn
Author-email: ryan.gerstenkorn@rhinosecuritylabs.com
Requires-Python: >=3.8,<4.0
Classifier: Programming Language :: Python :: 3
Classifier: Programming Language :: Python :: 3.8
Classifier: Programming Language :: Python :: 3.9
Classifier: Programming Language :: Python :: 3.10
Classifier: Programming Language :: Python :: 3.11
Classifier: Programming Language :: Python :: 3.12
Classifier: Programming Language :: Python :: 3.13
Provides-Extra: cli
Provides-Extra: scannerd
Requires-Dist: boto3 (>=1.16.0,<2.0.0)
Requires-Dist: typer (>=0.15.2,<0.16.0) ; extra == "cli"
Requires-Dist: urllib3 (>=1.26.4,<2.0.0)
